[
  {
    "type": "ShopProductPackageMaster",
    "Id": 1
  },
  {
    "type": "ShopProductPackageMaster",
    "Id": 2
  },
  {
    "type": "ShopProductPackageMaster",
    "Id": 3
  },
  {
    "type": "ShopProductPackageMaster",
    "Id": 4
  },
  {
    "type": "ShopProductPackageMaster",
    "Id": 5
  },
  {
    "type": "ShopProductPackageMaster",
    "Id": 6
  },
  {
    "type": "ShopProductPackageMaster",
    "Id": 7
  },
  {
    "type": "ShopProductPackageMaster",
    "Id": 8
  },
  {
    "type": "ShopProductPackageMaster",
    "Id": 9
  },
  {
    "type": "ShopProductPackageMaster",
    "Id": 10
  },
  {
    "type": "ShopProductPackageMaster",
    "Id": 11
  },
  {
    "type": "ShopProductPackageMaster",
    "Id": 12
  },
  {
    "type": "ShopProductPackageMaster",
    "Id": 13
  },
  {
    "type": "ShopProductPackageMaster",
    "Id": 14
  },
  {
    "type": "ShopProductPackageMaster",
    "Id": 15
  },
  {
    "type": "ShopProductPackageMaster",
    "Id": 16
  },
  {
    "type": "ShopProductPackageMaster",
    "Id": 17
  },
  {
    "type": "ShopProductPackageMaster",
    "Id": 18
  },
  {
    "type": "ShopProductPackageMaster",
    "Id": 19
  },
  {
    "type": "ShopProductPackageMaster",
    "Id": 20
  },
  {
    "type": "ShopProductPackageMaster",
    "Id": 21
  },
  {
    "type": "ShopProductPackageMaster",
    "Id": 22
  },
  {
    "type": "ShopProductPackageMaster",
    "Id": 23
  },
  {
    "type": "ShopProductPackageMaster",
    "Id": 24
  },
  {
    "type": "ShopProductPackageMaster",
    "Id": 25
  },
  {
    "type": "ShopProductPackageMaster",
    "Id": 26
  },
  {
    "type": "ShopProductPackageMaster",
    "Id": 27
  },
  {
    "type": "ShopProductPackageMaster",
    "Id": 28
  },
  {
    "type": "ShopProductPackageMaster",
    "Id": 29
  },
  {
    "type": "ShopProductPackageMaster",
    "Id": 30
  },
  {
    "type": "ShopProductPackageMaster",
    "Id": 31
  },
  {
    "type": "ShopProductPackageMaster",
    "Id": 32
  },
  {
    "type": "ShopProductPackageMaster",
    "Id": 33
  },
  {
    "type": "ShopProductPackageMaster",
    "Id": 34
  },
  {
    "type": "ShopProductPackageMaster",
    "Id": 35
  },
  {
    "type": "ShopProductPackageMaster",
    "Id": 36
  },
  {
    "type": "ShopProductPackageMaster",
    "Id": 37
  },
  {
    "type": "ShopProductPackageMaster",
    "Id": 38
  },
  {
    "type": "ShopProductPackageMaster",
    "Id": 39
  },
  {
    "type": "ShopProductPackageMaster",
    "Id": 40
  },
  {
    "type": "ShopProductPackageMaster",
    "Id": 41
  },
  {
    "type": "ShopProductPackageMaster",
    "Id": 42
  },
  {
    "type": "ShopProductPackageMaster",
    "Id": 43
  },
  {
    "type": "ShopProductPackageMaster",
    "Id": 44
  },
  {
    "type": "ShopProductPackageMaster",
    "Id": 45
  },
  {
    "type": "ShopProductPackageMaster",
    "Id": 46
  },
  {
    "type": "ShopProductPackageMaster",
    "Id": 47
  },
  {
    "type": "ShopProductPackageMaster",
    "Id": 48
  },
  {
    "type": "ShopProductPackageMaster",
    "Id": 49
  },
  {
    "type": "ShopProductPackageMaster",
    "Id": 50
  },
  {
    "type": "ShopProductPackageMaster",
    "Id": 51
  },
  {
    "type": "ShopProductPackageMaster",
    "Id": 52
  },
  {
    "type": "ShopProductPackageMaster",
    "Id": 53
  },
  {
    "type": "ShopProductPackageMaster",
    "Id": 54
  },
  {
    "type": "ShopProductPackageMaster",
    "Id": 55
  },
  {
    "type": "ShopProductPackageMaster",
    "Id": 56
  },
  {
    "type": "ShopProductPackageMaster",
    "Id": 57
  }
]